kg_rabbitmqonline/__init__.py
kg_rabbitmqonline/builder.py
kg_rabbitmqonline/configfile.py
kg_rabbitmqonline/option.py
kg_rabbitmqonline/py.typed
kg_rabbitmqonline/tests/__init__.py
kg_rabbitmqonline/tests/test_builder.py
tests/__init__.py
tests/test_builder.py
kg_rabbitmqonline-0.8.2.dist-info/LICENSE
kg_rabbitmqonline-0.8.2.dist-info/METADATA
kg_rabbitmqonline-0.8.2.dist-info/WHEEL
kg_rabbitmqonline-0.8.2.dist-info/top_level.txt
kg_rabbitmqonline-0.8.2.dist-info/RECORD
